{
  "item": [
    {
      "id": "d04b4576-d3b5-4594-a8c4-a0f3201b6018",
      "name": "Search",
      "description": {
        "content": "Search",
        "type": "text/plain"
      },
      "item": [
        {
          "id": "6776723c-94d6-47f9-9bd6-67f3b8b100ae",
          "name": "Search for Nodes in the Workspace (streaming)",
          "request": {
            "name": "Search for Nodes in the Workspace (streaming)",
            "description": {
              "content": "Search for nodes in the workspace with SSE streaming",
              "type": "text/plain"
            },
            "url": {
              "path": [
                "api",
                "v1",
                "w",
                ":wId",
                "search"
              ],
              "host": [
                "{{baseUrl}}"
              ],
              "query": [
                {
                  "disabled": false,
                  "key": "query",
                  "value": "<string>",
                  "description": "(Required) The search query (minimum 3 characters)"
                },
                {
                  "disabled": false,
                  "key": "limit",
                  "value": "<integer>",
                  "description": "Number of results per page (1-100, default 25)"
                },
                {
                  "disabled": false,
                  "key": "cursor",
                  "value": "<string>",
                  "description": "Cursor for pagination"
                },
                {
                  "disabled": false,
                  "key": "viewType",
                  "value": "<string>",
                  "description": "Type of view to filter results"
                },
                {
                  "disabled": false,
                  "key": "spaceIds",
                  "value": "<string>",
                  "description": "Comma-separated list of space IDs to search in"
                },
                {
                  "disabled": false,
                  "key": "includeDataSources",
                  "value": "<boolean>",
                  "description": "Whether to include data sources"
                },
                {
                  "disabled": false,
                  "key": "searchSourceUrls",
                  "value": "<boolean>",
                  "description": "Whether to search source URLs"
                },
                {
                  "disabled": false,
                  "key": "includeTools",
                  "value": "<boolean>",
                  "description": "Whether to include tool results"
                }
              ],
              "variable": [
                {
                  "disabled": false,
                  "type": "any",
                  "value": "<string>",
                  "key": "wId",
                  "description": "(Required) ID of the workspace"
                }
              ]
            },
            "header": [
              {
                "key": "Accept",
                "value": "text/event-stream"
              }
            ],
            "method": "GET",
            "auth": {
              "type": "bearer",
              "bearer": [
                {
                  "key": "token",
                  "value": "{{bearerToken}}"
                }
              ]
            }
          },
          "response": [
            {
              "id": "35ed004f-378d-42bc-9603-371e7773cbf5",
              "name": "Search results streamed successfully",
              "originalRequest": {
                "url": {
                  "path": [
                    "api",
                    "v1",
                    "w",
                    ":wId",
                    "search"
                  ],
                  "host": [
                    "{{baseUrl}}"
                  ],
                  "query": [
                    {
                      "key": "query",
                      "value": "<string>"
                    },
                    {
                      "key": "limit",
                      "value": "<integer>"
                    },
                    {
                      "key": "cursor",
                      "value": "<string>"
                    },
                    {
                      "key": "viewType",
                      "value": "<string>"
                    },
                    {
                      "key": "spaceIds",
                      "value": "<string>"
                    },
                    {
                      "key": "includeDataSources",
                      "value": "<boolean>"
                    },
                    {
                      "key": "searchSourceUrls",
                      "value": "<boolean>"
                    },
                    {
                      "key": "includeTools",
                      "value": "<boolean>"
                    }
                  ],
                  "variable": [
                    {
                      "disabled": false,
                      "type": "any",
                      "value": "<string>",
                      "key": "wId",
                      "description": "(Required) ID of the workspace"
                    }
                  ]
                },
                "header": [
                  {
                    "description": {
                      "content": "Added as a part of security scheme: bearer",
                      "type": "text/plain"
                    },
                    "key": "Authorization",
                    "value": "Bearer <token>"
                  },
                  {
                    "key": "Accept",
                    "value": "text/event-stream"
                  }
                ],
                "method": "GET",
                "body": {}
              },
              "status": "OK",
              "code": 200,
              "header": [
                {
                  "key": "Content-Type",
                  "value": "text/event-stream"
                }
              ],
              "body": "string",
              "cookie": [],
              "_postman_previewlanguage": "text"
            },
            {
              "id": "82e1008d-0561-4a41-b997-e631630b7ed2",
              "name": "Bad request",
              "originalRequest": {
                "url": {
                  "path": [
                    "api",
                    "v1",
                    "w",
                    ":wId",
                    "search"
                  ],
                  "host": [
                    "{{baseUrl}}"
                  ],
                  "query": [
                    {
                      "key": "query",
                      "value": "<string>"
                    },
                    {
                      "key": "limit",
                      "value": "<integer>"
                    },
                    {
                      "key": "cursor",
                      "value": "<string>"
                    },
                    {
                      "key": "viewType",
                      "value": "<string>"
                    },
                    {
                      "key": "spaceIds",
                      "value": "<string>"
                    },
                    {
                      "key": "includeDataSources",
                      "value": "<boolean>"
                    },
                    {
                      "key": "searchSourceUrls",
                      "value": "<boolean>"
                    },
                    {
                      "key": "includeTools",
                      "value": "<boolean>"
                    }
                  ],
                  "variable": [
                    {
                      "disabled": false,
                      "type": "any",
                      "value": "<string>",
                      "key": "wId",
                      "description": "(Required) ID of the workspace"
                    }
                  ]
                },
                "header": [
                  {
                    "description": {
                      "content": "Added as a part of security scheme: bearer",
                      "type": "text/plain"
                    },
                    "key": "Authorization",
                    "value": "Bearer <token>"
                  }
                ],
                "method": "GET",
                "body": {}
              },
              "status": "Bad Request",
              "code": 400,
              "header": [
                {
                  "key": "Content-Type",
                  "value": "text/plain"
                }
              ],
              "body": "",
              "cookie": [],
              "_postman_previewlanguage": "text"
            },
            {
              "id": "03d480e8-8d69-4c9f-bb06-e697e96fc0f2",
              "name": "Unauthorized",
              "originalRequest": {
                "url": {
                  "path": [
                    "api",
                    "v1",
                    "w",
                    ":wId",
                    "search"
                  ],
                  "host": [
                    "{{baseUrl}}"
                  ],
                  "query": [
                    {
                      "key": "query",
                      "value": "<string>"
                    },
                    {
                      "key": "limit",
                      "value": "<integer>"
                    },
                    {
                      "key": "cursor",
                      "value": "<string>"
                    },
                    {
                      "key": "viewType",
                      "value": "<string>"
                    },
                    {
                      "key": "spaceIds",
                      "value": "<string>"
                    },
                    {
                      "key": "includeDataSources",
                      "value": "<boolean>"
                    },
                    {
                      "key": "searchSourceUrls",
                      "value": "<boolean>"
                    },
                    {
                      "key": "includeTools",
                      "value": "<boolean>"
                    }
                  ],
                  "variable": [
                    {
                      "disabled": false,
                      "type": "any",
                      "value": "<string>",
                      "key": "wId",
                      "description": "(Required) ID of the workspace"
                    }
                  ]
                },
                "header": [
                  {
                    "description": {
                      "content": "Added as a part of security scheme: bearer",
                      "type": "text/plain"
                    },
                    "key": "Authorization",
                    "value": "Bearer <token>"
                  }
                ],
                "method": "GET",
                "body": {}
              },
              "status": "Unauthorized",
              "code": 401,
              "header": [
                {
                  "key": "Content-Type",
                  "value": "text/plain"
                }
              ],
              "body": "",
              "cookie": [],
              "_postman_previewlanguage": "text"
            },
            {
              "id": "911cb96c-8cd1-498a-8040-433bf5a92130",
              "name": "Method not allowed",
              "originalRequest": {
                "url": {
                  "path": [
                    "api",
                    "v1",
                    "w",
                    ":wId",
                    "search"
                  ],
                  "host": [
                    "{{baseUrl}}"
                  ],
                  "query": [
                    {
                      "key": "query",
                      "value": "<string>"
                    },
                    {
                      "key": "limit",
                      "value": "<integer>"
                    },
                    {
                      "key": "cursor",
                      "value": "<string>"
                    },
                    {
                      "key": "viewType",
                      "value": "<string>"
                    },
                    {
                      "key": "spaceIds",
                      "value": "<string>"
                    },
                    {
                      "key": "includeDataSources",
                      "value": "<boolean>"
                    },
                    {
                      "key": "searchSourceUrls",
                      "value": "<boolean>"
                    },
                    {
                      "key": "includeTools",
                      "value": "<boolean>"
                    }
                  ],
                  "variable": [
                    {
                      "disabled": false,
                      "type": "any",
                      "value": "<string>",
                      "key": "wId",
                      "description": "(Required) ID of the workspace"
                    }
                  ]
                },
                "header": [
                  {
                    "description": {
                      "content": "Added as a part of security scheme: bearer",
                      "type": "text/plain"
                    },
                    "key": "Authorization",
                    "value": "Bearer <token>"
                  }
                ],
                "method": "GET",
                "body": {}
              },
              "status": "Method Not Allowed",
              "code": 405,
              "header": [
                {
                  "key": "Content-Type",
                  "value": "text/plain"
                }
              ],
              "body": "",
              "cookie": [],
              "_postman_previewlanguage": "text"
            }
          ],
          "event": [],
          "protocolProfileBehavior": {
            "disableBodyPruning": true
          }
        },
        {
          "id": "8b35c580-2abd-4cf4-94d7-51ef2b9a7914",
          "name": "Search for Nodes in the Workspace",
          "request": {
            "name": "Search for Nodes in the Workspace",
            "description": {
              "content": "Search for nodes in the workspace",
              "type": "text/plain"
            },
            "url": {
              "path": [
                "api",
                "v1",
                "w",
                ":wId",
                "search"
              ],
              "host": [
                "{{baseUrl}}"
              ],
              "query": [],
              "variable": [
                {
                  "disabled": false,
                  "type": "any",
                  "value": "<string>",
                  "key": "wId",
                  "description": "(Required) ID of the workspace"
                }
              ]
            },
            "header": [
              {
                "key": "Content-Type",
                "value": "application/json"
              }
            ],
            "method": "POST",
            "auth": {
              "type": "bearer",
              "bearer": [
                {
                  "key": "token",
                  "value": "{{bearerToken}}"
                }
              ]
            },
            "body": {
              "mode": "raw",
              "raw": "{\n  \"query\": \"<string>\",\n  \"includeDataSources\": \"<boolean>\",\n  \"viewType\": \"<string>\",\n  \"spaceIds\": [\n    \"<string>\",\n    \"<string>\"\n  ],\n  \"nodeIds\": [\n    \"<string>\",\n    \"<string>\"\n  ],\n  \"searchSourceUrls\": \"<boolean>\"\n}",
              "options": {
                "raw": {
                  "language": "json"
                }
              }
            }
          },
          "response": [
            {
              "id": "2c1beecb-9bf6-4da4-8a99-11c2e072fb28",
              "name": "Search results retrieved successfully",
              "originalRequest": {
                "url": {
                  "path": [
                    "api",
                    "v1",
                    "w",
                    ":wId",
                    "search"
                  ],
                  "host": [
                    "{{baseUrl}}"
                  ],
                  "query": [],
                  "variable": [
                    {
                      "disabled": false,
                      "type": "any",
                      "value": "<string>",
                      "key": "wId",
                      "description": "(Required) ID of the workspace"
                    }
                  ]
                },
                "header": [
                  {
                    "description": {
                      "content": "Added as a part of security scheme: bearer",
                      "type": "text/plain"
                    },
                    "key": "Authorization",
                    "value": "Bearer <token>"
                  }
                ],
                "method": "POST",
                "body": {
                  "mode": "raw",
                  "raw": "{\n  \"query\": \"<string>\",\n  \"includeDataSources\": \"<boolean>\",\n  \"viewType\": \"<string>\",\n  \"spaceIds\": [\n    \"<string>\",\n    \"<string>\"\n  ],\n  \"nodeIds\": [\n    \"<string>\",\n    \"<string>\"\n  ],\n  \"searchSourceUrls\": \"<boolean>\"\n}",
                  "options": {
                    "raw": {
                      "language": "json"
                    }
                  }
                }
              },
              "status": "OK",
              "code": 200,
              "header": [
                {
                  "key": "Content-Type",
                  "value": "text/plain"
                }
              ],
              "body": "",
              "cookie": [],
              "_postman_previewlanguage": "text"
            },
            {
              "id": "f1ded4cb-689d-42c5-8601-232a5583952d",
              "name": "Bad request",
              "originalRequest": {
                "url": {
                  "path": [
                    "api",
                    "v1",
                    "w",
                    ":wId",
                    "search"
                  ],
                  "host": [
                    "{{baseUrl}}"
                  ],
                  "query": [],
                  "variable": [
                    {
                      "disabled": false,
                      "type": "any",
                      "value": "<string>",
                      "key": "wId",
                      "description": "(Required) ID of the workspace"
                    }
                  ]
                },
                "header": [
                  {
                    "description": {
                      "content": "Added as a part of security scheme: bearer",
                      "type": "text/plain"
                    },
                    "key": "Authorization",
                    "value": "Bearer <token>"
                  }
                ],
                "method": "POST",
                "body": {
                  "mode": "raw",
                  "raw": "{\n  \"query\": \"<string>\",\n  \"includeDataSources\": \"<boolean>\",\n  \"viewType\": \"<string>\",\n  \"spaceIds\": [\n    \"<string>\",\n    \"<string>\"\n  ],\n  \"nodeIds\": [\n    \"<string>\",\n    \"<string>\"\n  ],\n  \"searchSourceUrls\": \"<boolean>\"\n}",
                  "options": {
                    "raw": {
                      "language": "json"
                    }
                  }
                }
              },
              "status": "Bad Request",
              "code": 400,
              "header": [
                {
                  "key": "Content-Type",
                  "value": "text/plain"
                }
              ],
              "body": "",
              "cookie": [],
              "_postman_previewlanguage": "text"
            },
            {
              "id": "12276e96-4a06-48b5-b136-ee11eaa7d2eb",
              "name": "Unauthorized",
              "originalRequest": {
                "url": {
                  "path": [
                    "api",
                    "v1",
                    "w",
                    ":wId",
                    "search"
                  ],
                  "host": [
                    "{{baseUrl}}"
                  ],
                  "query": [],
                  "variable": [
                    {
                      "disabled": false,
                      "type": "any",
                      "value": "<string>",
                      "key": "wId",
                      "description": "(Required) ID of the workspace"
                    }
                  ]
                },
                "header": [
                  {
                    "description": {
                      "content": "Added as a part of security scheme: bearer",
                      "type": "text/plain"
                    },
                    "key": "Authorization",
                    "value": "Bearer <token>"
                  }
                ],
                "method": "POST",
                "body": {
                  "mode": "raw",
                  "raw": "{\n  \"query\": \"<string>\",\n  \"includeDataSources\": \"<boolean>\",\n  \"viewType\": \"<string>\",\n  \"spaceIds\": [\n    \"<string>\",\n    \"<string>\"\n  ],\n  \"nodeIds\": [\n    \"<string>\",\n    \"<string>\"\n  ],\n  \"searchSourceUrls\": \"<boolean>\"\n}",
                  "options": {
                    "raw": {
                      "language": "json"
                    }
                  }
                }
              },
              "status": "Unauthorized",
              "code": 401,
              "header": [
                {
                  "key": "Content-Type",
                  "value": "text/plain"
                }
              ],
              "body": "",
              "cookie": [],
              "_postman_previewlanguage": "text"
            },
            {
              "id": "3da674e7-3f45-49a8-9cfe-aaf34887aabf",
              "name": "Space not found",
              "originalRequest": {
                "url": {
                  "path": [
                    "api",
                    "v1",
                    "w",
                    ":wId",
                    "search"
                  ],
                  "host": [
                    "{{baseUrl}}"
                  ],
                  "query": [],
                  "variable": [
                    {
                      "disabled": false,
                      "type": "any",
                      "value": "<string>",
                      "key": "wId",
                      "description": "(Required) ID of the workspace"
                    }
                  ]
                },
                "header": [
                  {
                    "description": {
                      "content": "Added as a part of security scheme: bearer",
                      "type": "text/plain"
                    },
                    "key": "Authorization",
                    "value": "Bearer <token>"
                  }
                ],
                "method": "POST",
                "body": {
                  "mode": "raw",
                  "raw": "{\n  \"query\": \"<string>\",\n  \"includeDataSources\": \"<boolean>\",\n  \"viewType\": \"<string>\",\n  \"spaceIds\": [\n    \"<string>\",\n    \"<string>\"\n  ],\n  \"nodeIds\": [\n    \"<string>\",\n    \"<string>\"\n  ],\n  \"searchSourceUrls\": \"<boolean>\"\n}",
                  "options": {
                    "raw": {
                      "language": "json"
                    }
                  }
                }
              },
              "status": "Not Found",
              "code": 404,
              "header": [
                {
                  "key": "Content-Type",
                  "value": "text/plain"
                }
              ],
              "body": "",
              "cookie": [],
              "_postman_previewlanguage": "text"
            },
            {
              "id": "8d069c78-6f84-45c1-9df0-ed84189f0587",
              "name": "Method not allowed",
              "originalRequest": {
                "url": {
                  "path": [
                    "api",
                    "v1",
                    "w",
                    ":wId",
                    "search"
                  ],
                  "host": [
                    "{{baseUrl}}"
                  ],
                  "query": [],
                  "variable": [
                    {
                      "disabled": false,
                      "type": "any",
                      "value": "<string>",
                      "key": "wId",
                      "description": "(Required) ID of the workspace"
                    }
                  ]
                },
                "header": [
                  {
                    "description": {
                      "content": "Added as a part of security scheme: bearer",
                      "type": "text/plain"
                    },
                    "key": "Authorization",
                    "value": "Bearer <token>"
                  }
                ],
                "method": "POST",
                "body": {
                  "mode": "raw",
                  "raw": "{\n  \"query\": \"<string>\",\n  \"includeDataSources\": \"<boolean>\",\n  \"viewType\": \"<string>\",\n  \"spaceIds\": [\n    \"<string>\",\n    \"<string>\"\n  ],\n  \"nodeIds\": [\n    \"<string>\",\n    \"<string>\"\n  ],\n  \"searchSourceUrls\": \"<boolean>\"\n}",
                  "options": {
                    "raw": {
                      "language": "json"
                    }
                  }
                }
              },
              "status": "Method Not Allowed",
              "code": 405,
              "header": [
                {
                  "key": "Content-Type",
                  "value": "text/plain"
                }
              ],
              "body": "",
              "cookie": [],
              "_postman_previewlanguage": "text"
            }
          ],
          "event": [],
          "protocolProfileBehavior": {
            "disableBodyPruning": true
          }
        },
        {
          "id": "64660c8d-0f3c-4d64-b3ec-4dd705bbeaa2",
          "name": "Upload a Tool File",
          "request": {
            "name": "Upload a Tool File",
            "description": {
              "content": "Download and upload a file from a tool (MCP server) to Dust",
              "type": "text/plain"
            },
            "url": {
              "path": [
                "api",
                "v1",
                "w",
                ":wId",
                "search",
                "tools",
                "upload"
              ],
              "host": [
                "{{baseUrl}}"
              ],
              "query": [],
              "variable": [
                {
                  "disabled": false,
                  "type": "any",
                  "value": "<string>",
                  "key": "wId",
                  "description": "(Required) ID of the workspace"
                }
              ]
            },
            "header": [
              {
                "key": "Content-Type",
                "value": "application/json"
              }
            ],
            "method": "POST",
            "auth": {
              "type": "bearer",
              "bearer": [
                {
                  "key": "token",
                  "value": "{{bearerToken}}"
                }
              ]
            },
            "body": {
              "mode": "raw",
              "raw": "{\n  \"serverViewId\": \"<string>\",\n  \"externalId\": \"<string>\",\n  \"conversationId\": \"<string>\",\n  \"serverName\": \"<string>\",\n  \"serverIcon\": \"<string>\"\n}",
              "options": {
                "raw": {
                  "language": "json"
                }
              }
            }
          },
          "response": [
            {
              "id": "c10924b5-97e0-4b1a-aaa5-4fb1fcd4d4f2",
              "name": "File uploaded successfully",
              "originalRequest": {
                "url": {
                  "path": [
                    "api",
                    "v1",
                    "w",
                    ":wId",
                    "search",
                    "tools",
                    "upload"
                  ],
                  "host": [
                    "{{baseUrl}}"
                  ],
                  "query": [],
                  "variable": [
                    {
                      "disabled": false,
                      "type": "any",
                      "value": "<string>",
                      "key": "wId",
                      "description": "(Required) ID of the workspace"
                    }
                  ]
                },
                "header": [
                  {
                    "description": {
                      "content": "Added as a part of security scheme: bearer",
                      "type": "text/plain"
                    },
                    "key": "Authorization",
                    "value": "Bearer <token>"
                  }
                ],
                "method": "POST",
                "body": {
                  "mode": "raw",
                  "raw": "{\n  \"serverViewId\": \"<string>\",\n  \"externalId\": \"<string>\",\n  \"conversationId\": \"<string>\",\n  \"serverName\": \"<string>\",\n  \"serverIcon\": \"<string>\"\n}",
                  "options": {
                    "raw": {
                      "language": "json"
                    }
                  }
                }
              },
              "status": "OK",
              "code": 200,
              "header": [
                {
                  "key": "Content-Type",
                  "value": "text/plain"
                }
              ],
              "body": "",
              "cookie": [],
              "_postman_previewlanguage": "text"
            },
            {
              "id": "fda46374-51db-4479-8e94-9434f922bc28",
              "name": "Bad request",
              "originalRequest": {
                "url": {
                  "path": [
                    "api",
                    "v1",
                    "w",
                    ":wId",
                    "search",
                    "tools",
                    "upload"
                  ],
                  "host": [
                    "{{baseUrl}}"
                  ],
                  "query": [],
                  "variable": [
                    {
                      "disabled": false,
                      "type": "any",
                      "value": "<string>",
                      "key": "wId",
                      "description": "(Required) ID of the workspace"
                    }
                  ]
                },
                "header": [
                  {
                    "description": {
                      "content": "Added as a part of security scheme: bearer",
                      "type": "text/plain"
                    },
                    "key": "Authorization",
                    "value": "Bearer <token>"
                  }
                ],
                "method": "POST",
                "body": {
                  "mode": "raw",
                  "raw": "{\n  \"serverViewId\": \"<string>\",\n  \"externalId\": \"<string>\",\n  \"conversationId\": \"<string>\",\n  \"serverName\": \"<string>\",\n  \"serverIcon\": \"<string>\"\n}",
                  "options": {
                    "raw": {
                      "language": "json"
                    }
                  }
                }
              },
              "status": "Bad Request",
              "code": 400,
              "header": [
                {
                  "key": "Content-Type",
                  "value": "text/plain"
                }
              ],
              "body": "",
              "cookie": [],
              "_postman_previewlanguage": "text"
            },
            {
              "id": "dce274b5-7f1a-445f-a4e6-8a38057a4ee1",
              "name": "Unauthorized",
              "originalRequest": {
                "url": {
                  "path": [
                    "api",
                    "v1",
                    "w",
                    ":wId",
                    "search",
                    "tools",
                    "upload"
                  ],
                  "host": [
                    "{{baseUrl}}"
                  ],
                  "query": [],
                  "variable": [
                    {
                      "disabled": false,
                      "type": "any",
                      "value": "<string>",
                      "key": "wId",
                      "description": "(Required) ID of the workspace"
                    }
                  ]
                },
                "header": [
                  {
                    "description": {
                      "content": "Added as a part of security scheme: bearer",
                      "type": "text/plain"
                    },
                    "key": "Authorization",
                    "value": "Bearer <token>"
                  }
                ],
                "method": "POST",
                "body": {
                  "mode": "raw",
                  "raw": "{\n  \"serverViewId\": \"<string>\",\n  \"externalId\": \"<string>\",\n  \"conversationId\": \"<string>\",\n  \"serverName\": \"<string>\",\n  \"serverIcon\": \"<string>\"\n}",
                  "options": {
                    "raw": {
                      "language": "json"
                    }
                  }
                }
              },
              "status": "Unauthorized",
              "code": 401,
              "header": [
                {
                  "key": "Content-Type",
                  "value": "text/plain"
                }
              ],
              "body": "",
              "cookie": [],
              "_postman_previewlanguage": "text"
            },
            {
              "id": "35859555-4ff9-4e04-aadd-50610bd97f02",
              "name": "Method not allowed",
              "originalRequest": {
                "url": {
                  "path": [
                    "api",
                    "v1",
                    "w",
                    ":wId",
                    "search",
                    "tools",
                    "upload"
                  ],
                  "host": [
                    "{{baseUrl}}"
                  ],
                  "query": [],
                  "variable": [
                    {
                      "disabled": false,
                      "type": "any",
                      "value": "<string>",
                      "key": "wId",
                      "description": "(Required) ID of the workspace"
                    }
                  ]
                },
                "header": [
                  {
                    "description": {
                      "content": "Added as a part of security scheme: bearer",
                      "type": "text/plain"
                    },
                    "key": "Authorization",
                    "value": "Bearer <token>"
                  }
                ],
                "method": "POST",
                "body": {
                  "mode": "raw",
                  "raw": "{\n  \"serverViewId\": \"<string>\",\n  \"externalId\": \"<string>\",\n  \"conversationId\": \"<string>\",\n  \"serverName\": \"<string>\",\n  \"serverIcon\": \"<string>\"\n}",
                  "options": {
                    "raw": {
                      "language": "json"
                    }
                  }
                }
              },
              "status": "Method Not Allowed",
              "code": 405,
              "header": [
                {
                  "key": "Content-Type",
                  "value": "text/plain"
                }
              ],
              "body": "",
              "cookie": [],
              "_postman_previewlanguage": "text"
            },
            {
              "id": "45e65df3-4540-4cb5-8d51-41e832f8cd3e",
              "name": "Internal server error",
              "originalRequest": {
                "url": {
                  "path": [
                    "api",
                    "v1",
                    "w",
                    ":wId",
                    "search",
                    "tools",
                    "upload"
                  ],
                  "host": [
                    "{{baseUrl}}"
                  ],
                  "query": [],
                  "variable": [
                    {
                      "disabled": false,
                      "type": "any",
                      "value": "<string>",
                      "key": "wId",
                      "description": "(Required) ID of the workspace"
                    }
                  ]
                },
                "header": [
                  {
                    "description": {
                      "content": "Added as a part of security scheme: bearer",
                      "type": "text/plain"
                    },
                    "key": "Authorization",
                    "value": "Bearer <token>"
                  }
                ],
                "method": "POST",
                "body": {
                  "mode": "raw",
                  "raw": "{\n  \"serverViewId\": \"<string>\",\n  \"externalId\": \"<string>\",\n  \"conversationId\": \"<string>\",\n  \"serverName\": \"<string>\",\n  \"serverIcon\": \"<string>\"\n}",
                  "options": {
                    "raw": {
                      "language": "json"
                    }
                  }
                }
              },
              "status": "Internal Server Error",
              "code": 500,
              "header": [
                {
                  "key": "Content-Type",
                  "value": "text/plain"
                }
              ],
              "body": "",
              "cookie": [],
              "_postman_previewlanguage": "text"
            }
          ],
          "event": [],
          "protocolProfileBehavior": {
            "disableBodyPruning": true
          }
        }
      ],
      "event": []
    }
  ],
  "event": [],
  "variable": [
    {
      "type": "string",
      "value": "https://dust.tt",
      "key": "baseUrl"
    }
  ],
  "info": {
    "_postman_id": "3aa4367c-0c99-4ca6-aed3-987197e7bb91",
    "name": "Dust Search API",
    "schema": "https://schema.getpostman.com/json/collection/v2.1.0/collection.json",
    "description": {
      "content": "Search nodes (documents, tables, conversations) across a workspace with optional streaming.\n\nContact Support:\n Name: Dust Support",
      "type": "text/plain"
    }
  }
}